LICENSE
MANIFEST.in
README.md
requirements.txt
setup.cfg
setup.py
django_mp_static.egg-info/PKG-INFO
django_mp_static.egg-info/SOURCES.txt
django_mp_static.egg-info/dependency_links.txt
django_mp_static.egg-info/requires.txt
django_mp_static.egg-info/top_level.txt
static/__init__.py
static/settings.py