Metadata-Version: 1.1
Name: django-mp-static
Version: 0.1
Summary: Django static app
Home-page: https://github.com/pmaigutyak/mp-static
Author: Paul Maigutyak
Author-email: pmaigutyak@gmail.com
License: MIT
Download-URL: https://github.com/pmaigutyak/mp-static/archive/0.1.tar.gz
Platform: UNKNOWN
